CalcBeat.py
FMCW_chirp_linearity.py
FS2dBm.py
Friis.py
README.rst
SAR.py
SimChirp.py
ToneFinder.py
comm.f90
fwdmodel.f90
setup.py
tincanradar/__init__.py
tincanradar/fwdmodel.py
tincanradar/plots.py
tincanradar/windowavg.py
tincanradar.egg-info/PKG-INFO
tincanradar.egg-info/SOURCES.txt
tincanradar.egg-info/dependency_links.txt
tincanradar.egg-info/requires.txt
tincanradar.egg-info/top_level.txt